fuzzdex-1.2.0.dist-info/METADATA
fuzzdex-1.2.0.dist-info/WHEEL
fuzzdex-1.2.0.dist-info/licenses/LICENSE
fuzzdex/__init__.py
fuzzdex/fuzzdex.cpython-313-x86_64-linux-gnu.so
fuzzdex-1.2.0.dist-info/RECORD
