Metadata-Version: 2.4
Name: fuzzdex
Version: 1.2.0
Classifier: Programming Language :: Rust
Classifier: Programming Language :: Python :: Implementation :: CPython
Classifier: Development Status :: 5 - Production/Stable
Classifier: Topic :: Text Processing :: Indexing
Classifier: Topic :: Text Processing :: Linguistic
Classifier: Topic :: Scientific/Engineering :: GIS
Classifier: License :: OSI Approved :: MIT License
License-File: LICENSE
Keywords: fuzzy,dictionary,geocoding
Home-Page: https://github.com/blaa/fuzzdex
Author: Tomasz bla Fortuna <bla@thera.be>
Author-email: Tomasz bla Fortuna <bla@thera.be>
License: MIT
Requires-Python: >=3.7
